thestage/.env
thestage/__init__.py
thestage/__main__.py
thestage/cli_command.py
thestage/cli_command_helper.py
thestage/color_scheme/__init__.py
thestage/color_scheme/color_scheme.py
thestage/config/__init__.py
thestage/config/business/__init__.py
thestage/config/business/app_config_service.py
thestage/config/business/config_provider.py
thestage/config/business/config_storage.py
thestage/config/business/validation_service.py
thestage/config/communication/__init__.py
thestage/config/communication/config_command.py
thestage/config/dto/__init__.py
thestage/config/dto/config_entity.py
thestage/config/dto/remote_server_config.py
thestage/config/env_base.py
thestage/connect/__init__.py
thestage/connect/business/__init__.py
thestage/connect/business/connect_service.py
thestage/connect/business/remote_server_service.py
thestage/connect/communication/__init__.py
thestage/connect/communication/connect_api_client.py
thestage/connect/dto/__init__.py
thestage/connect/dto/add_ssh_key_to_user_request.py
thestage/connect/dto/add_ssh_key_to_user_response.py
thestage/connect/dto/add_ssh_public_key_to_instance_request.py
thestage/connect/dto/add_ssh_public_key_to_instance_response.py
thestage/connect/dto/connect_resolve_response.py
thestage/connect/dto/is_user_has_public_ssh_key_request.py
thestage/connect/dto/is_user_has_public_ssh_key_response.py
thestage/controllers/__init__.py
thestage/controllers/base_controller.py
thestage/controllers/utils_controller.py
thestage/debug_main.dist.py
thestage/docker_container/__init__.py
thestage/docker_container/business/__init__.py
thestage/docker_container/business/container_service.py
thestage/docker_container/business/mapper/__init__.py
thestage/docker_container/business/mapper/container_mapper.py
thestage/docker_container/communication/__init__.py
thestage/docker_container/communication/docker_command.py
thestage/docker_container/communication/docker_container_api_client.py
thestage/docker_container/dto/__init__.py
thestage-0.6.8.dist-info/METADATA
thestage-0.6.8.dist-info/WHEEL
thestage-0.6.8.dist-info/entry_points.txt
thestage-0.6.8.dist-info/licenses/LICENSE.txt
thestage-0.6.8.dist-info/RECORD
