Metadata-Version: 2.4
Name: thestage
Version: 0.6.8
Summary: 
License-File: LICENSE.txt
Author: TheStage AI team
Author-email: hello@thestage.ai
Requires-Python: >=3.9,<=3.13
Classifier: Programming Language :: Python :: 3
Classifier: Programming Language :: Python :: 3.9
Classifier: Programming Language :: Python :: 3.10
Classifier: Programming Language :: Python :: 3.11
Classifier: Programming Language :: Python :: 3.12
Classifier: Programming Language :: Python :: 3.13
Requires-Dist: aioconsole (>=0.8.0,<0.9.0)
Requires-Dist: boto3 (>=1.35.80,<2.0.0)
Requires-Dist: gitpython (>=3.1.40,<4.0.0)
Requires-Dist: httpx (>=0.27.2,<0.28.0)
Requires-Dist: paramiko (>=3.5.1,<4.0.0)
Requires-Dist: pydantic (>=2.4.2,<3.0.0)
Requires-Dist: python-dotenv (>=1.0.0,<2.0.0)
Requires-Dist: python-gettext-translations (>=1.1.0,<2.0.0)
Requires-Dist: requests (>=2.31.0,<3.0.0)
Requires-Dist: rich (>=14.2.0,<15.0.0)
Requires-Dist: tabulate (>=0.9.0,<0.10.0)
Requires-Dist: typer[all] (>=0.15.2,<0.16.0)
